pgn_to_gif/__init__.py
pgn_to_gif/cli.py
pgn_to_gif/utils.py
pgn_to_gif-0.0.3.dist-info/LICENSE
pgn_to_gif-0.0.3.dist-info/METADATA
pgn_to_gif-0.0.3.dist-info/WHEEL
pgn_to_gif-0.0.3.dist-info/entry_points.txt
pgn_to_gif-0.0.3.dist-info/top_level.txt
pgn_to_gif-0.0.3.dist-info/RECORD
