Metadata-Version: 2.1
Name: pgn-to-gif
Version: 0.0.3
Summary: Generate GIFs of chess games from PGN files.
Home-page: https://github.com/afozk95/pgn-to-gif
Author: Ahmed Furkan Özkalay
Author-email: afozk95@gmail.com
License: MIT
Keywords: chess,gif,pgn
Platform: UNKNOWN
Classifier: License :: OSI Approved :: MIT License
Classifier: Programming Language :: Python :: 3
Classifier: Programming Language :: Python :: 3.8
Requires-Python: >=3.6
Requires-Dist: cairosvg
Requires-Dist: imageio
Requires-Dist: python-chess
